{"info":{"file":"legacy/scripts/backend/matrix.js","fileShort":"legacy/scripts/backend/matrix.js","fileSafe":"legacy_scripts_backend_matrix_js","link":"files/legacy_scripts_backend_matrix_js/index.html"},"complexity":{"aggregate":{"sloc":{"logical":127,"physical":295},"cyclomatic":20,"halstead":{"operators":{"distinct":19,"total":241,"identifiers":["__stripped__"]},"operands":{"distinct":43,"total":371,"identifiers":["__stripped__"]},"length":612,"vocabulary":62,"difficulty":81.96511627906976,"volume":3643.968141956768,"effort":298678.27247271227,"bugs":1.2146560473189225,"time":16593.237359595125},"params":27,"line":8,"cyclomaticDensity":15.748031496062993,"complexity":{"cyclomatic":20,"sloc":{"logical":127,"physical":295},"halstead":{"operators":{"distinct":19,"total":241,"identifiers":["__stripped__"]},"operands":{"distinct":43,"total":371,"identifiers":["__stripped__"]},"length":612,"vocabulary":62,"difficulty":81.96511627906976,"volume":3643.968141956768,"effort":298678.27247271227,"bugs":1.2146560473189225,"time":16593.237359595125}}},"functions":[{"name":"clear","sloc":{"logical":1,"physical":5},"cyclomatic":1,"halstead":{"operators":{"distinct":1,"total":1,"identifiers":["__stripped__"]},"operands":{"distinct":1,"total":1,"identifiers":["__stripped__"]},"length":2,"vocabulary":2,"difficulty":0.5,"volume":2,"effort":1,"bugs":0.0006666666666666666,"time":0.05555555555555555},"params":0,"line":16,"cyclomaticDensity":100,"complexity":{"cyclomatic":1,"sloc":{"logical":1,"physical":5},"halstead":{"operators":{"distinct":1,"total":1,"identifiers":["__stripped__"]},"operands":{"distinct":1,"total":1,"identifiers":["__stripped__"]},"length":2,"vocabulary":2,"difficulty":0.5,"volume":2,"effort":1,"bugs":0.0006666666666666666,"time":0.05555555555555555}}},{"name":"clone","sloc":{"logical":2,"physical":5},"cyclomatic":1,"halstead":{"operators":{"distinct":3,"total":3,"identifiers":["__stripped__"]},"operands":{"distinct":2,"total":3,"identifiers":["__stripped__"]},"length":6,"vocabulary":5,"difficulty":2.25,"volume":13.931568569324174,"effort":31.34602928097939,"bugs":0.004643856189774725,"time":1.7414460711655217},"params":0,"line":21,"cyclomaticDensity":50,"complexity":{"cyclomatic":1,"sloc":{"logical":2,"physical":5},"halstead":{"operators":{"distinct":3,"total":3,"identifiers":["__stripped__"]},"operands":{"distinct":2,"total":3,"identifiers":["__stripped__"]},"length":6,"vocabulary":5,"difficulty":2.25,"volume":13.931568569324174,"effort":31.34602928097939,"bugs":0.004643856189774725,"time":1.7414460711655217}}},{"name":"erase","sloc":{"logical":1,"physical":4},"cyclomatic":1,"halstead":{"operators":{"distinct":1,"total":1,"identifiers":["__stripped__"]},"operands":{"distinct":2,"total":2,"identifiers":["__stripped__"]},"length":3,"vocabulary":3,"difficulty":0.5,"volume":4.754887502163469,"effort":2.3774437510817346,"bugs":0.0015849625007211565,"time":0.1320802083934297},"params":1,"line":26,"cyclomaticDensity":100,"complexity":{"cyclomatic":1,"sloc":{"logical":1,"physical":4},"halstead":{"operators":{"distinct":1,"total":1,"identifiers":["__stripped__"]},"operands":{"distinct":2,"total":2,"identifiers":["__stripped__"]},"length":3,"vocabulary":3,"difficulty":0.5,"volume":4.754887502163469,"effort":2.3774437510817346,"bugs":0.0015849625007211565,"time":0.1320802083934297}}},{"name":"extend","sloc":{"logical":1,"physical":5},"cyclomatic":1,"halstead":{"operators":{"distinct":1,"total":1,"identifiers":["__stripped__"]},"operands":{"distinct":2,"total":2,"identifiers":["__stripped__"]},"length":3,"vocabulary":3,"difficulty":0.5,"volume":4.754887502163469,"effort":2.3774437510817346,"bugs":0.0015849625007211565,"time":0.1320802083934297},"params":1,"line":30,"cyclomaticDensity":100,"complexity":{"cyclomatic":1,"sloc":{"logical":1,"physical":5},"halstead":{"operators":{"distinct":1,"total":1,"identifiers":["__stripped__"]},"operands":{"distinct":2,"total":2,"identifiers":["__stripped__"]},"length":3,"vocabulary":3,"difficulty":0.5,"volume":4.754887502163469,"effort":2.3774437510817346,"bugs":0.0015849625007211565,"time":0.1320802083934297}}},{"name":"get","sloc":{"logical":1,"physical":4},"cyclomatic":1,"halstead":{"operators":{"distinct":1,"total":1,"identifiers":["__stripped__"]},"operands":{"distinct":3,"total":3,"identifiers":["__stripped__"]},"length":4,"vocabulary":4,"difficulty":0.5,"volume":8,"effort":4,"bugs":0.0026666666666666666,"time":0.2222222222222222},"params":2,"line":35,"cyclomaticDensity":100,"complexity":{"cyclomatic":1,"sloc":{"logical":1,"physical":4},"halstead":{"operators":{"distinct":1,"total":1,"identifiers":["__stripped__"]},"operands":{"distinct":3,"total":3,"identifiers":["__stripped__"]},"length":4,"vocabulary":4,"difficulty":0.5,"volume":8,"effort":4,"bugs":0.0026666666666666666,"time":0.2222222222222222}}},{"name":"set","sloc":{"logical":1,"physical":4},"cyclomatic":1,"halstead":{"operators":{"distinct":1,"total":1,"identifiers":["__stripped__"]},"operands":{"distinct":4,"total":4,"identifiers":["__stripped__"]},"length":5,"vocabulary":5,"difficulty":0.5,"volume":11.60964047443681,"effort":5.804820237218405,"bugs":0.0038698801581456034,"time":0.32249001317880027},"params":3,"line":39,"cyclomaticDensity":100,"complexity":{"cyclomatic":1,"sloc":{"logical":1,"physical":4},"halstead":{"operators":{"distinct":1,"total":1,"identifiers":["__stripped__"]},"operands":{"distinct":4,"total":4,"identifiers":["__stripped__"]},"length":5,"vocabulary":5,"difficulty":0.5,"volume":11.60964047443681,"effort":5.804820237218405,"bugs":0.0038698801581456034,"time":0.32249001317880027}}},{"name":"equalSize","sloc":{"logical":1,"physical":3},"cyclomatic":1,"halstead":{"operators":{"distinct":5,"total":10,"identifiers":["__stripped__"]},"operands":{"distinct":5,"total":12,"identifiers":["__stripped__"]},"length":22,"vocabulary":10,"difficulty":6,"volume":73.08241808752197,"effort":438.49450852513183,"bugs":0.024360806029173992,"time":24.36080602917399},"params":2,"line":54,"cyclomaticDensity":100,"complexity":{"cyclomatic":1,"sloc":{"logical":1,"physical":3},"halstead":{"operators":{"distinct":5,"total":10,"identifiers":["__stripped__"]},"operands":{"distinct":5,"total":12,"identifiers":["__stripped__"]},"length":22,"vocabulary":10,"difficulty":6,"volume":73.08241808752197,"effort":438.49450852513183,"bugs":0.024360806029173992,"time":24.36080602917399}}},{"name":"getRow","sloc":{"logical":8,"physical":12},"cyclomatic":2,"halstead":{"operators":{"distinct":9,"total":14,"identifiers":["__stripped__"]},"operands":{"distinct":9,"total":23,"identifiers":["__stripped__"]},"length":37,"vocabulary":18,"difficulty":11.5,"volume":154.28722505336555,"effort":1774.3030881137038,"bugs":0.05142907501778852,"time":98.57239378409466},"params":2,"line":67,"cyclomaticDensity":25,"complexity":{"cyclomatic":2,"sloc":{"logical":8,"physical":12},"halstead":{"operators":{"distinct":9,"total":14,"identifiers":["__stripped__"]},"operands":{"distinct":9,"total":23,"identifiers":["__stripped__"]},"length":37,"vocabulary":18,"difficulty":11.5,"volume":154.28722505336555,"effort":1774.3030881137038,"bugs":0.05142907501778852,"time":98.57239378409466}}},{"name":"getCol","sloc":{"logical":8,"physical":12},"cyclomatic":2,"halstead":{"operators":{"distinct":9,"total":14,"identifiers":["__stripped__"]},"operands":{"distinct":9,"total":23,"identifiers":["__stripped__"]},"length":37,"vocabulary":18,"difficulty":11.5,"volume":154.28722505336555,"effort":1774.3030881137038,"bugs":0.05142907501778852,"time":98.57239378409466},"params":2,"line":89,"cyclomaticDensity":25,"complexity":{"cyclomatic":2,"sloc":{"logical":8,"physical":12},"halstead":{"operators":{"distinct":9,"total":14,"identifiers":["__stripped__"]},"operands":{"distinct":9,"total":23,"identifiers":["__stripped__"]},"length":37,"vocabulary":18,"difficulty":11.5,"volume":154.28722505336555,"effort":1774.3030881137038,"bugs":0.05142907501778852,"time":98.57239378409466}}},{"name":"rowSum","sloc":{"logical":8,"physical":12},"cyclomatic":2,"halstead":{"operators":{"distinct":8,"total":12,"identifiers":["__stripped__"]},"operands":{"distinct":8,"total":22,"identifiers":["__stripped__"]},"length":34,"vocabulary":16,"difficulty":11,"volume":136,"effort":1496,"bugs":0.04533333333333334,"time":83.11111111111111},"params":2,"line":111,"cyclomaticDensity":25,"complexity":{"cyclomatic":2,"sloc":{"logical":8,"physical":12},"halstead":{"operators":{"distinct":8,"total":12,"identifiers":["__stripped__"]},"operands":{"distinct":8,"total":22,"identifiers":["__stripped__"]},"length":34,"vocabulary":16,"difficulty":11,"volume":136,"effort":1496,"bugs":0.04533333333333334,"time":83.11111111111111}}},{"name":"rowSums","sloc":{"logical":8,"physical":12},"cyclomatic":2,"halstead":{"operators":{"distinct":9,"total":14,"identifiers":["__stripped__"]},"operands":{"distinct":9,"total":22,"identifiers":["__stripped__"]},"length":36,"vocabulary":18,"difficulty":11,"volume":150.11730005192322,"effort":1651.2903005711555,"bugs":0.05003910001730774,"time":91.73835003173086},"params":1,"line":131,"cyclomaticDensity":25,"complexity":{"cyclomatic":2,"sloc":{"logical":8,"physical":12},"halstead":{"operators":{"distinct":9,"total":14,"identifiers":["__stripped__"]},"operands":{"distinct":9,"total":22,"identifiers":["__stripped__"]},"length":36,"vocabulary":18,"difficulty":11,"volume":150.11730005192322,"effort":1651.2903005711555,"bugs":0.05003910001730774,"time":91.73835003173086}}},{"name":"mult","sloc":{"logical":18,"physical":27},"cyclomatic":6,"halstead":{"operators":{"distinct":12,"total":37,"identifiers":["__stripped__"]},"operands":{"distinct":17,"total":59,"identifiers":["__stripped__"]},"length":96,"vocabulary":29,"difficulty":20.823529411764707,"volume":466.366175532247,"effort":9711.389772847966,"bugs":0.15545539184408233,"time":539.5216540471092},"params":3,"line":156,"cyclomaticDensity":33.33333333333333,"complexity":{"cyclomatic":6,"sloc":{"logical":18,"physical":27},"halstead":{"operators":{"distinct":12,"total":37,"identifiers":["__stripped__"]},"operands":{"distinct":17,"total":59,"identifiers":["__stripped__"]},"length":96,"vocabulary":29,"difficulty":20.823529411764707,"volume":466.366175532247,"effort":9711.389772847966,"bugs":0.15545539184408233,"time":539.5216540471092}}},{"name":"multVec","sloc":{"logical":11,"physical":15},"cyclomatic":4,"halstead":{"operators":{"distinct":11,"total":23,"identifiers":["__stripped__"]},"operands":{"distinct":10,"total":36,"identifiers":["__stripped__"]},"length":59,"vocabulary":21,"difficulty":19.8,"volume":259.14672794394687,"effort":5131.105213290149,"bugs":0.08638224264798229,"time":285.0614007383416},"params":2,"line":195,"cyclomaticDensity":36.36363636363637,"complexity":{"cyclomatic":4,"sloc":{"logical":11,"physical":15},"halstead":{"operators":{"distinct":11,"total":23,"identifiers":["__stripped__"]},"operands":{"distinct":10,"total":36,"identifiers":["__stripped__"]},"length":59,"vocabulary":21,"difficulty":19.8,"volume":259.14672794394687,"effort":5131.105213290149,"bugs":0.08638224264798229,"time":285.0614007383416}}},{"name":"colSum","sloc":{"logical":8,"physical":12},"cyclomatic":2,"halstead":{"operators":{"distinct":8,"total":12,"identifiers":["__stripped__"]},"operands":{"distinct":8,"total":22,"identifiers":["__stripped__"]},"length":34,"vocabulary":16,"difficulty":11,"volume":136,"effort":1496,"bugs":0.04533333333333334,"time":83.11111111111111},"params":2,"line":220,"cyclomaticDensity":25,"complexity":{"cyclomatic":2,"sloc":{"logical":8,"physical":12},"halstead":{"operators":{"distinct":8,"total":12,"identifiers":["__stripped__"]},"operands":{"distinct":8,"total":22,"identifiers":["__stripped__"]},"length":34,"vocabulary":16,"difficulty":11,"volume":136,"effort":1496,"bugs":0.04533333333333334,"time":83.11111111111111}}},{"name":"colSums","sloc":{"logical":8,"physical":12},"cyclomatic":2,"halstead":{"operators":{"distinct":9,"total":14,"identifiers":["__stripped__"]},"operands":{"distinct":9,"total":22,"identifiers":["__stripped__"]},"length":36,"vocabulary":18,"difficulty":11,"volume":150.11730005192322,"effort":1651.2903005711555,"bugs":0.05003910001730774,"time":91.73835003173086},"params":1,"line":240,"cyclomaticDensity":25,"complexity":{"cyclomatic":2,"sloc":{"logical":8,"physical":12},"halstead":{"operators":{"distinct":9,"total":14,"identifiers":["__stripped__"]},"operands":{"distinct":9,"total":22,"identifiers":["__stripped__"]},"length":36,"vocabulary":18,"difficulty":11,"volume":150.11730005192322,"effort":1651.2903005711555,"bugs":0.05003910001730774,"time":91.73835003173086}}},{"name":"transpose","sloc":{"logical":11,"physical":15},"cyclomatic":3,"halstead":{"operators":{"distinct":8,"total":21,"identifiers":["__stripped__"]},"operands":{"distinct":9,"total":39,"identifiers":["__stripped__"]},"length":60,"vocabulary":17,"difficulty":17.333333333333332,"volume":245.2477704750204,"effort":4250.961354900353,"bugs":0.08174925682500679,"time":236.1645197166863},"params":1,"line":260,"cyclomaticDensity":27.27272727272727,"complexity":{"cyclomatic":3,"sloc":{"logical":11,"physical":15},"halstead":{"operators":{"distinct":8,"total":21,"identifiers":["__stripped__"]},"operands":{"distinct":9,"total":39,"identifiers":["__stripped__"]},"length":60,"vocabulary":17,"difficulty":17.333333333333332,"volume":245.2477704750204,"effort":4250.961354900353,"bugs":0.08174925682500679,"time":236.1645197166863}}},{"name":"vecMult","sloc":{"logical":11,"physical":15},"cyclomatic":4,"halstead":{"operators":{"distinct":11,"total":23,"identifiers":["__stripped__"]},"operands":{"distinct":10,"total":36,"identifiers":["__stripped__"]},"length":59,"vocabulary":21,"difficulty":19.8,"volume":259.14672794394687,"effort":5131.105213290149,"bugs":0.08638224264798229,"time":285.0614007383416},"params":2,"line":287,"cyclomaticDensity":36.36363636363637,"complexity":{"cyclomatic":4,"sloc":{"logical":11,"physical":15},"halstead":{"operators":{"distinct":11,"total":23,"identifiers":["__stripped__"]},"operands":{"distinct":10,"total":36,"identifiers":["__stripped__"]},"length":59,"vocabulary":21,"difficulty":19.8,"volume":259.14672794394687,"effort":5131.105213290149,"bugs":0.08638224264798229,"time":285.0614007383416}}}],"dependencies":[],"maintainability":67.23706425473725,"loc":6.294117647058823,"cyclomatic":2.1176470588235294,"effort":2032.538151602578,"params":1.588235294117647,"module":"legacy/scripts/backend/matrix.js"},"jshint":{"messages":[]},"date":"2015-07-30T17:04:13.000Z"}